{
    "ahashpool":  [
                      "bitcore",
                      "blake2s",
                      "c11",
                      "groestl",
                      "hsr",
                      "lbry",
                      "Lyra2RE2",
                      "MyriadGroestl",
                      "neoscrypt",
                      "Nist5",
                      "phi",
                      "sib",
                      "skein",
                      "skunk",
                      "tribus",
                      "x17",
                      "xevan"
                  ],
    "ahashpool24hr":  [
                          "bitcore",
                          "blake2s",
                          "c11",
                          "groestl",
                          "hsr",
                          "lbry",
                          "Lyra2RE2",
                          "MyriadGroestl",
                          "neoscrypt",
                          "Nist5",
                          "phi",
                          "sib",
                          "skein",
                          "skunk",
                          "tribus",
                          "x17",
                          "xevan"
                      ],
    "ahashpoolPlus":  [
                          "bitcore",
                          "blake2s",
                          "c11",
                          "groestl",
                          "hsr",
                          "lbry",
                          "Lyra2RE2",
                          "MyriadGroestl",
                          "neoscrypt",
                          "Nist5",
                          "phi",
                          "sib",
                          "skein",
                          "skunk",
                          "tribus",
                          "x17",
                          "xevan"
                      ],
    "blazepool":  [
                      "bitcore",
                      "blake2s",
                      "blakecoin",
                      "c11",
                      "groestl",
                      "hsr",
                      "keccak",
                      "Lyra2RE2",
                      "neoscrypt",
                      "Nist5",
                      "phi",
                      "sib",
                      "skein",
                      "tribus",
                      "x17",
                      "xevan",
                      "yescrypt"
                  ],
    "blazepool24hr":  [
                          "bitcore",
                          "blake2s",
                          "blakecoin",
                          "c11",
                          "groestl",
                          "hsr",
                          "keccak",
                          "Lyra2RE2",
                          "neoscrypt",
                          "Nist5",
                          "phi",
                          "sib",
                          "skein",
                          "tribus",
                          "x17",
                          "xevan",
                          "yescrypt"
                      ],
    "blazepoolplus":  [
                          "bitcore",
                          "blake2s",
                          "blakecoin",
                          "c11",
                          "groestl",
                          "hsr",
                          "keccak",
                          "Lyra2RE2",
                          "neoscrypt",
                          "Nist5",
                          "phi",
                          "sib",
                          "skein",
                          "tribus",
                          "x17",
                          "xevan",
                          "yescrypt"
                      ],
    "hashrefinery":  [
                         "bitcore",
                         "Lyra2RE2",
                         "neoscrypt",
                         "Nist5",
                         "phi",
                         "skein",
                         "skunk",
                         "tribus",
                         "x17",
                         "xevan"
                     ],
    "minemoney":  [
                      "bitcore",
                      "blake2s",
                      "blakecoin",
                      "c11",
                      "groestl",
                      "hsr",
                      "keccak",
                      "lbry",
                      "Lyra2RE2",
                      "MyriadGroestl",
                      "neoscrypt",
                      "Nist5",
                      "phi",
                      "poly",
                      "sib",
                      "skein",
                      "skunk",
                      "timetravel",
                      "tribus",
                      "x11evo",
                      "x17",
                      "xevan"
                  ],
    "miningpoolhub":  [
                          "cryptonight",
                          "equihash",
                          "ethash",
                          "groestl",
                          "keccak",
                          "Lyra2RE2",
                          "lyra2z",
                          "MyriadGroestl",
                          "neoscrypt",
                          "skein"
                      ],
    "nicehash":  [
                     "blake2s",
                     "cryptonight",
                     "equihash",
                     "ethash",
                     "keccak",
                     "lbry",
                     "Lyra2RE2",
                     "neoscrypt",
                     "Nist5",
                     "skunk",
                     "x11gost"
                 ],
    "phiphipool":  [
                     "bitcore",
                     "blake2s",
                     "c11",
                     "groestl",
                     "hmq1725",
                     "keccak",
                     "keccakc",
                     "Lyra2RE2",
                     "lyra2z",
                     "neoscrypt",
                     "Nist5",
                     "phi",
                     "skunk",
                     "tribus",
                     "x16r",
                     "x16s",
                     "x17",
                     "xevan"
                 ],
    "phiphipool24hr":  [
                     "bitcore",
                     "blake2s",
                     "c11",
                     "groestl",
                     "hmq1725",
                     "keccak",
                     "keccakc",
                     "Lyra2RE2",
                     "lyra2z",
                     "neoscrypt",
                     "Nist5",
                     "phi",
                     "skunk",
                     "tribus",
                     "x16r",
                     "x16s",
                     "x17",
                     "xevan"
                 ],
    "phiphipoolplus":  [
                     "bitcore",
                     "blake2s",
                     "c11",
                     "groestl",
                     "hmq1725",
                     "keccak",
                     "keccakc",
                     "Lyra2RE2",
                     "lyra2z",
                     "neoscrypt",
                     "Nist5",
                     "phi",
                     "skunk",
                     "tribus",
                     "x16r",
                     "x16s",
                     "x17",
                     "xevan"
                 ],
    "zergpool":  [
                     "bitcore",
                     "blake2s",
                     "c11",
                     "groestl",
                     "hsr",
                     "keccakc",
                     "Lyra2RE2",
                     "lyra2z",
                     "MyriadGroestl",
                     "neoscrypt",
                     "Nist5",
                     "phi",
                     "sib",
                     "skein",
                     "skunk",
                     "tribus",
                     "x16r",
                     "x16s",
                     "x17",
                     "xevan"
                 ],
    "zergpool24hr":  [
                         "bitcore",
                         "blake2s",
                         "c11",
                         "groestl",
                         "hsr",
                         "keccakc",
                         "Lyra2RE2",
                         "lyra2z",
                         "MyriadGroestl",
                         "neoscrypt",
                         "Nist5",
                         "phi",
                         "sib",
                         "skein",
                         "skunk",
                         "tribus",
                         "x16r",
                         "x16s",
                         "x17",
                         "xevan"
                     ],
    "zergpoolplus":  [
                         "bitcore",
                         "blake2s",
                         "c11",
                         "groestl",
                         "hsr",
                         "keccakc",
                         "Lyra2RE2",
                         "lyra2z",
                         "MyriadGroestl",
                         "neoscrypt",
                         "Nist5",
                         "phi",
                         "sib",
                         "skein",
                         "skunk",
                         "tribus",
                         "x16r",
                         "x16s",
                         "x17",
                         "xevan"
                     ],
    "zpool":  [
                  "bitcore",
                  "blake2s",
                  "blakecoin",
                  "c11",
                  "equihash",
                  "groestl",
                  "hmq1725",
                  "hmq1725",
                  "hsr",
                  "keccakc",
                  "lbry",
                  "Lyra2RE2",
                  "lyra2z",
                  "MyriadGroestl",
                  "neoscrypt",
                  "Nist5",
                  "phi",
                  "poly",
                  "sib",
                  "skein",
                  "skunk",
                  "tribus",
                  "x11evo",
                  "x17",
                  "xevan"
              ],
    "zpool24hr":  [
                      "bitcore",
                      "blake2s",
                      "blakecoin",
                      "c11",
                      "equihash",
                      "groestl",
                      "hmq1725",
                      "hmq1725",
                      "hsr",
                      "keccakc",
                      "lbry",
                      "Lyra2RE2",
                      "lyra2z",
                      "MyriadGroestl",
                      "neoscrypt",
                      "Nist5",
                      "phi",
                      "poly",
                      "sib",
                      "skein",
                      "skunk",
                      "tribus",
                      "x11evo",
                      "x17",
                      "xevan"
                  ],
    "zpoolplus":  [
                      "bitcore",
                      "blake2s",
                      "blakecoin",
                      "c11",
                      "equihash",
                      "groestl",
                      "hmq1725",
                      "hmq1725",
                      "hsr",
                      "keccakc",
                      "lbry",
                      "Lyra2RE2",
                      "lyra2z",
                      "MyriadGroestl",
                      "neoscrypt",
                      "Nist5",
                      "phi",
                      "poly",
                      "sib",
                      "skein",
                      "skunk",
                      "tribus",
                      "x11evo",
                      "x17",
                      "xevan"
                  ]
}